{
  "concept_alien_zoo": {
    "concept_alien_zoo": {
      "icon": "gfx/interface/icons/buildings/building_xeno_zoo.dds"
    },
    "_source_file": "02_building_concepts.txt",
    "_line_number": 3
  },
  "concept_archaeostudies_faculty": {
    "concept_archaeostudies_faculty": {
      "icon": "gfx/interface/icons/buildings/building_archaeostudies_faculty.dds"
    },
    "_source_file": "02_building_concepts.txt",
    "_line_number": 7
  },
  "concept_bureaucratic_1": {
    "concept_bureaucratic_1": {
      "icon": "gfx/interface/icons/buildings/building_bureaucratic_1.dds"
    },
    "_source_file": "02_building_concepts.txt",
    "_line_number": 11
  },
  "concept_clinic": {
    "concept_clinic": {
      "icon": "gfx/interface/icons/buildings/building_clinic.dds"
    },
    "_source_file": "02_building_concepts.txt",
    "_line_number": 15
  },
  "concept_clone_army_clone_vat": {
    "concept_clone_army_clone_vat": {
      "icon": "gfx/interface/icons/buildings/building_ancient_relics.dds"
    },
    "_source_file": "02_building_concepts.txt",
    "_line_number": 19
  },
  "concept_commercial_zone": {
    "concept_commercial_zone": {
      "icon": "gfx/interface/icons/buildings/building_commercial_zone.dds"
    },
    "_source_file": "02_building_concepts.txt",
    "_line_number": 23
  },
  "concept_energy_grid": {
    "concept_energy_grid": {
      "icon": "gfx/interface/icons/buildings/building_energy_grid.dds"
    },
    "_source_file": "02_building_concepts.txt",
    "_line_number": 27
  },
  "concept_hab_capital": {
    "concept_hab_capital": {
      "icon": "gfx/interface/icons/buildings/building_capital.dds"
    },
    "_source_file": "02_building_concepts.txt",
    "_line_number": 31
  },
  "concept_hydroponics_farm": {
    "concept_hydroponics_farm": {
      "icon": "gfx/interface/icons/buildings/building_hydroponics_farm.dds"
    },
    "_source_file": "02_building_concepts.txt",
    "_line_number": 35
  },
  "concept_knight_commandery": {
    "concept_knight_commandery": {
      "icon": "gfx/interface/icons/buildings/building_order_holding.dds"
    },
    "_source_file": "02_building_concepts.txt",
    "_line_number": 39
  },
  "concept_low_tech_admin_hub": {
    "concept_low_tech_admin_hub": {
      "icon": "gfx/interface/icons/buildings/building_low_tech_admin_hub.dds"
    },
    "_source_file": "02_building_concepts.txt",
    "_line_number": 43
  },
  "concept_low_tech_capital": {
    "concept_low_tech_capital": {
      "icon": "gfx/interface/icons/buildings/building_low_tech_capital.dds"
    },
    "_source_file": "02_building_concepts.txt",
    "_line_number": 47
  },
  "concept_low_tech_farm": {
    "concept_low_tech_farm": {
      "icon": "gfx/interface/icons/buildings/building_low_tech_farm.dds"
    },
    "_source_file": "02_building_concepts.txt",
    "_line_number": 51
  },
  "concept_low_tech_power_plant": {
    "concept_low_tech_power_plant": {
      "icon": "gfx/interface/icons/buildings/building_low_tech_power_plant.dds"
    },
    "_source_file": "02_building_concepts.txt",
    "_line_number": 55
  },
  "concept_low_tech_research_lab": {
    "concept_low_tech_research_lab": {
      "icon": "gfx/interface/icons/buildings/building_low_tech_research_lab.dds"
    },
    "_source_file": "02_building_concepts.txt",
    "_line_number": 59
  },
  "concept_low_tech_scrap_refinery": {
    "concept_low_tech_scrap_refinery": {
      "icon": "gfx/interface/icons/buildings/building_low_tech_scrap_refinery.dds"
    },
    "_source_file": "02_building_concepts.txt",
    "_line_number": 63
  },
  "concept_military_academy": {
    "concept_military_academy": {
      "icon": "gfx/interface/icons/buildings/building_military_academy.dds"
    },
    "_source_file": "02_building_concepts.txt",
    "_line_number": 67
  },
  "concept_mineral_purification_plant": {
    "concept_mineral_purification_plant": {
      "icon": "gfx/interface/icons/buildings/building_mineral_purification_plant.dds"
    },
    "_source_file": "02_building_concepts.txt",
    "_line_number": 71
  },
  "concept_necrophage_elevation_chamber": {
    "concept_necrophage_elevation_chamber": {
      "icon": "gfx/interface/icons/buildings/building_chamber_of_elevation_1.dds"
    },
    "_source_file": "02_building_concepts.txt",
    "_line_number": 75
  },
  "concept_noble_estates": {
    "concept_noble_estates": {
      "icon": "gfx/interface/icons/buildings/building_palace.dds"
    },
    "_source_file": "02_building_concepts.txt",
    "_line_number": 79
  },
  "concept_noble_vacation_homes": {
    "concept_noble_vacation_homes": {
      "icon": "gfx/interface/icons/buildings/building_palace.dds"
    },
    "_source_file": "02_building_concepts.txt",
    "_line_number": 83
  },
  "concept_offspring_holding": {
    "concept_offspring_holding": {
      "icon": "gfx/interface/icons/buildings/building_offspring_nest.dds"
    },
    "_source_file": "02_building_concepts.txt",
    "_line_number": 87
  },
  "concept_offspring_nests": {
    "concept_offspring_nests": {
      "icon": "gfx/interface/icons/buildings/building_offspring_nest.dds"
    },
    "_source_file": "02_building_concepts.txt",
    "_line_number": 91
  },
  "concept_order_keep": {
    "concept_order_keep": {
      "icon": "gfx/interface/icons/buildings/building_order_keep.dds"
    },
    "_source_file": "02_building_concepts.txt",
    "_line_number": 95
  },
  "concept_research_lab": {
    "concept_research_lab": {
      "icon": "gfx/interface/icons/buildings/building_research_lab_1.dds"
    },
    "_source_file": "02_building_concepts.txt",
    "_line_number": 99
  },
  "concept_robot_assembly_plant": {
    "concept_robot_assembly_plant": {
      "icon": "gfx/interface/icons/buildings/building_robot_assembly_plant.dds"
    },
    "_source_file": "02_building_concepts.txt",
    "_line_number": 103
  },
  "concept_sacrificial_shrine": {
    "concept_sacrificial_shrine": {
      "icon": "gfx/interface/icons/buildings/building_sacrificial_temple_2.dds"
    },
    "_source_file": "02_building_concepts.txt",
    "_line_number": 107
  },
  "concept_sacrificial_temple": {
    "concept_sacrificial_temple": {
      "icon": "gfx/interface/icons/buildings/building_sacrificial_temple_1.dds"
    },
    "_source_file": "02_building_concepts.txt",
    "_line_number": 111
  },
  "concept_spawning_pools": {
    "concept_spawning_pools": {
      "icon": "gfx/interface/icons/buildings/building_spawning_pool.dds"
    },
    "_source_file": "02_building_concepts.txt",
    "_line_number": 115
  },
  "concept_tree_of_life_holding": {
    "concept_tree_of_life_holding": {
      "icon": "gfx/interface/icons/buildings/holding_tree_of_life_sapling.dds"
    },
    "_source_file": "02_building_concepts.txt",
    "_line_number": 119
  }
}