{
  "MACHINE1": {
    "MACHINE1": {
      "category": "Machine",
      "should_name_home_system_planets": "no",
      "ship_names": {
        "generic": {},
        "corvette": {},
        "destroyer": {},
        "cruiser": {},
        "battleship": {},
        "titan": {},
        "colossus": {},
        "juggernaut": {},
        "science": {},
        "colonizer": {},
        "sponsored_colonizer": {},
        "constructor": {},
        "transport": {},
        "military_station_small": {},
        "ion_cannon": {}
      },
      "fleet_names": {
        "random_names": {},
        "sequential_name": "MACHINE1_LEGION"
      },
      "army_names": {
        "generic": {
          "sequential_name": "MACHINE1_MECHANIZEDASSAULTFORCE"
        },
        "machine_assault_1": {
          "sequential_name": "MACHINE1_MECHANIZEDASSAULTFORCE"
        },
        "machine_defense": {
          "sequential_name": "MACHINE1_MECHANIZEDDEFENSEFORCE"
        },
        "machine_assault_2": {
          "sequential_name": "MACHINE1_HEAVYASSAULTFORCE"
        },
        "machine_assault_3": {
          "sequential_name": "MACHINE1_ASSAULTTITANULTRA"
        },
        "defense_army": {
          "sequential_name": "MACHINE1_CYBORGDEFENSEFORCE"
        },
        "assault_army": {
          "sequential_name": "MACHINE1_MECHANIZEDCYBORGFORCE"
        },
        "clone_army": {
          "sequential_name": "MACHINE1_MECHANIZEDCLONEFORCE"
        },
        "slave_army": {
          "sequential_name": "MACHINE1_MECHANIZEDINDENTUREDFORCE"
        },
        "undead_army": {
          "sequential_name": "MACHINE1_MECHANIZEDUNDEADFORCE"
        },
        "robotic_army": {
          "sequential_name": "MACHINE1_AUTOMATONFORCE"
        },
        "psionic_army": {
          "sequential_name": "MACHINE2_PSIBOTS"
        },
        "xenomorph_army": {
          "sequential_name": "MACHINE1_XENOFORCE"
        },
        "gene_warrior_army": {
          "sequential_name": "MACHINE1_FLESHFORCE"
        },
        "occupation_army": {
          "sequential_name": "MACHINE1_OCCUPYINGFORCE"
        },
        "individual_machine_occupation_army": {
          "sequential_name": "MACHINE1_OCCUPYINGFORCE"
        },
        "robotic_occupation_army": {
          "sequential_name": "MACHINE3_AUTOMATEDPROTECTORS"
        },
        "machine_occupation_army": {
          "sequential_name": "MACHINE1_MECHANIZEDGARRISONFORCE"
        },
        "robotic_defense_army": {
          "sequential_name": "MACHINE1_AUTOMATEDOCCUPIERS"
        },
        "primitive_army": {
          "sequential_name": "MACHINE1_PRIMITIVEARMY"
        },
        "industrial_army": {
          "sequential_name": "MACHINE1_INDUSTRIALARMY"
        },
        "postatomic_army": {
          "sequential_name": "MACHINE1_POSTATOMICARMY"
        },
        "warpling_army": {
          "sequential_name": "seq_warpling_army"
        }
      },
      "_comments": [
        "### PLANETS"
      ],
      "planet_names": {
        "generic": {
          "names": {}
        },
        "pc_desert": {
          "names": {}
        },
        "pc_tropical": {
          "names": {}
        },
        "pc_arid": {
          "names": {}
        },
        "pc_continental": {
          "names": {}
        },
        "pc_ocean": {
          "names": {}
        },
        "pc_tundra": {
          "names": {}
        },
        "pc_arctic": {
          "names": {}
        },
        "pc_savannah": {
          "names": {}
        },
        "pc_alpine": {
          "names": {}
        },
        "pc_nuked": {
          "names": {}
        }
      },
      "character_names": {
        "default": {
          "_comments": [
            "# A complete name"
          ],
          "full_names": {},
          "regnal_full_names": {}
        }
      }
    },
    "_source_file": "MACHINE1.txt",
    "_line_number": 60
  }
}