{
  "00_agreement_presets.txt": {
    "# name_of_preset": {
      "_source_file": "<RECURSION>",
      "_line_number": 5
    },
    "preset_vassal": {
      "preset_vassal": {
        "icon": "GFX_diplomacy_status_is_vassal",
        "term_data": {
          "discrete_terms": {}
        },
        "overlord_weight": {
          "base": "100"
        },
        "subject_weight": {
          "base": "25"
        },
        "potential": {
          "from": {
            "NOR": {
              "is_megacorp": "yes",
              "is_country_type": "awakened_fallen_empire",
              "has_civic": "civic_inwards_perfection"
            }
          },
          "NOT": {
            "OR": {
              "from": {
                "tech_unlocked_ratio": {
                  "who": "from",
                  "ratio >": "@protectorate_tech_threshold"
                }
              }
            }
          }
        }
      },
      "<RECURSION>": 38
    },
    "preset_subsidiary": {
      "preset_subsidiary": {
        "icon": "GFX_diplomacy_status_is_subsidiary",
        "term_data": {
          "discrete_terms": {},
          "resource_terms": {}
        },
        "overlord_weight": {
          "base": "100"
        },
        "subject_weight": {
          "base": "50"
        },
        "potential": {
          "from": {
            "tech_unlocked_ratio": {
              "who": "from",
              "ratio >": "@protectorate_tech_threshold"
            }
          }
        }
      },
      "<RECURSION>": 108
    },
    "preset_tributary": {
      "preset_tributary": {
        "icon": "GFX_diplomacy_status_is_tributary",
        "term_data": {
          "discrete_terms": {},
          "resource_terms": {}
        },
        "overlord_weight": {
          "base": "90"
        },
        "subject_weight": {
          "base": "50"
        },
        "potential": {
          "from": {
            "NOR": {
              "is_megacorp": "yes",
              "is_country_type": "awakened_fallen_empire"
            }
          },
          "tech_unlocked_ratio": {
            "who": "from",
            "ratio >": "@protectorate_tech_threshold"
          }
        }
      },
      "<RECURSION>": 173
    },
    "preset_bulwark": {
      "preset_bulwark": {
        "specialist_type": "specialist_bulwark",
        "term_data": {
          "resource_terms": {},
          "discrete_terms": {}
        },
        "overlord_weight": {
          "base": "@specialist_base_acceptance_value",
          "modifier": {
            "factor": "0.5",
            "has_specialist_subject_type": {
              "NOT": {},
              "modifier": {
                "factor": "1.5",
                "FROM": {},
                "modifier": {
                  "factor": "1.2"
                }
              },
              "subject_weight": {
                "base": "25",
                "modifier": {
                  "add": "@specialist_unaligned_ethics_value",
                  "is_pacifist": "yes"
                }
              },
              "potential": {
                "has_overlord_dlc": "yes",
                "NOR": {
                  "has_civic": "civic_inwards_perfection",
                  "FROM": {},
                  "OR": {
                    "FROM": {
                      "is_specialist_subject_type": {
                        "has_country_flag": "specialistion_subject_conversion_flag",
                        "tech_unlocked_ratio": {
                          "who": "from",
                          "ratio >": "@protectorate_tech_threshold"
                        },
                        "has_origin": "origin_enlightened"
                      }
                    }
                  }
                }
              }
            }
          }
        }
      },
      "<RECURSION>": 244
    },
    "preset_scholarium": {
      "preset_scholarium": {
        "specialist_type": "specialist_scholarium",
        "term_data": {
          "discrete_terms": {}
        },
        "overlord_weight": {
          "base": "@specialist_base_acceptance_value",
          "modifier": {
            "factor": "0.5",
            "has_specialist_subject_type": {
              "NOT": {},
              "modifier": {
                "factor": "1.5",
                "FROM": {}
              },
              "subject_weight": {
                "base": "@specialist_subject_base_acceptance_value",
                "modifier": {
                  "add": "@specialist_unaligned_ethics_value",
                  "is_spiritualist": "yes"
                }
              },
              "potential": {
                "has_overlord_dlc": "yes",
                "NOR": {
                  "has_civic": "civic_inwards_perfection",
                  "FROM": {},
                  "OR": {
                    "FROM": {
                      "is_specialist_subject_type": {
                        "has_country_flag": "specialistion_subject_conversion_flag",
                        "tech_unlocked_ratio": {
                          "who": "from",
                          "ratio >": "@protectorate_tech_threshold"
                        },
                        "has_origin": "origin_enlightened"
                      }
                    }
                  }
                }
              }
            }
          }
        }
      },
      "<RECURSION>": 345
    },
    "preset_prospectorium": {
      "preset_prospectorium": {
        "specialist_type": "specialist_prospectorium",
        "term_data": {
          "resource_terms": {},
          "discrete_terms": {}
        },
        "overlord_weight": {
          "base": "@specialist_base_acceptance_value",
          "modifier": {
            "factor": "0.5",
            "has_specialist_subject_type": {
              "NOT": {},
              "modifier": {
                "factor": "1.5",
                "FROM": {}
              },
              "subject_weight": {
                "base": "@specialist_subject_base_acceptance_value",
                "modifier": {
                  "add": "@specialist_unaligned_ethics_value",
                  "is_militarist": "yes"
                }
              },
              "potential": {
                "has_overlord_dlc": "yes",
                "NOR": {
                  "has_civic": "civic_inwards_perfection",
                  "FROM": {},
                  "OR": {
                    "FROM": {
                      "is_specialist_subject_type": {
                        "has_country_flag": "specialistion_subject_conversion_flag",
                        "tech_unlocked_ratio": {
                          "who": "from",
                          "ratio >": "@protectorate_tech_threshold"
                        },
                        "has_origin": "origin_enlightened"
                      }
                    }
                  }
                }
              }
            }
          }
        }
      },
      "<RECURSION>": 436
    },
    "preset_release_sector": {
      "preset_release_sector": {
        "term_data": {
          "has_cooldown_on_first_renegotiation": "no",
          "forced_initial_loyalty": "50"
        },
        "hidden": "yes",
        "should_ai_use_for_proposals": "no"
      },
      "<RECURSION>": 530
    },
    "preset_protectorate": {
      "preset_protectorate": {
        "icon": "GFX_diplomacy_status_is_protectorate",
        "term_data": {
          "discrete_terms": {}
        },
        "potential": {
          "from": {
            "NOT": {
              "has_origin": "origin_imperial_vassal_overlord"
            },
            "is_country_type": "default"
          },
          "has_been_declared_crisis": "no",
          "NOT": {
            "tech_unlocked_ratio": {
              "who": "from"
            }
          },
          "overlord_weight": {
            "base": "200"
          },
          "subject_weight": {
            "base": "50"
          }
        }
      },
      "<RECURSION>": 545
    },
    "preset_scion": {
      "preset_scion": {
        "icon": "GFX_diplomacy_status_is_scion",
        "term_data": {
          "discrete_terms": {}
        },
        "potential": {
          "any_agreement": {
            "agreement_preset": "preset_scion"
          },
          "from": {
            "OR": {
              "is_country_type": "awakened_fallen_empire"
            }
          }
        }
      },
      "<RECURSION>": 605
    },
    "preset_dominion": {
      "preset_dominion": {
        "icon": "GFX_diplomacy_status_is_dominion",
        "term_data": {
          "discrete_terms": {},
          "resource_terms": {}
        },
        "potential": {
          "from": {
            "is_country_type": "awakened_fallen_empire",
            "has_ethic": "ethic_fanatic_spiritualist"
          }
        }
      },
      "<RECURSION>": 671
    },
    "preset_satellite": {
      "preset_satellite": {
        "icon": "GFX_diplomacy_status_is_satellite",
        "term_data": {
          "discrete_terms": {},
          "resource_terms": {}
        },
        "potential": {
          "from": {
            "is_country_type": "awakened_fallen_empire",
            "has_ethic": "ethic_fanatic_materialist"
          }
        }
      },
      "<RECURSION>": 723
    },
    "preset_signatory": {
      "preset_signatory": {
        "icon": "GFX_diplomacy_status_is_signatory",
        "term_data": {
          "discrete_terms": {}
        },
        "potential": {
          "from": {
            "is_country_type": "awakened_fallen_empire",
            "has_ethic": "ethic_fanatic_xenophile"
          }
        }
      },
      "<RECURSION>": 775
    },
    "preset_thrall": {
      "preset_thrall": {
        "icon": "GFX_diplomacy_status_is_thrall",
        "term_data": {
          "discrete_terms": {},
          "resource_terms": {}
        },
        "potential": {
          "from": {
            "is_country_type": "awakened_fallen_empire",
            "has_ethic": "ethic_fanatic_xenophobe"
          }
        }
      },
      "<RECURSION>": 821
    },
    "preset_satrapy": {
      "preset_satrapy": {
        "icon": "GFX_diplomacy_status_is_satrapy",
        "term_data": {
          "discrete_terms": {},
          "resource_terms": {}
        },
        "potential": {
          "from": {
            "is_country_type": "awakened_marauders"
          }
        }
      },
      "<RECURSION>": 873
    },
    "preset_relic_satrapy": {
      "preset_relic_satrapy": {
        "icon": "GFX_diplomacy_status_is_satrapy",
        "term_data": {
          "discrete_terms": {},
          "resource_terms": {}
        },
        "potential": {
          "from": {
            "has_relic": "r_khans_throne"
          }
        }
      },
      "<RECURSION>": 928
    }
  },
  "01_agreement_presets_ai_subsidiary.txt": {
    "preset_subsidiary_mean_01": {
      "preset_subsidiary_mean_01": {
        "parent": "preset_subsidiary",
        "icon": "GFX_diplomacy_status_is_subsidiary",
        "hidden": "yes",
        "term_data": {
          "resource_terms": {},
          "discrete_terms": {}
        },
        "overlord_weight": {
          "base": "125"
        },
        "subject_weight": {
          "base": "-100"
        },
        "potential": {
          "from": {}
        }
      },
      "<RECURSION>": 2
    },
    "preset_subsidiary_mean_02": {
      "preset_subsidiary_mean_02": {
        "parent": "preset_subsidiary",
        "icon": "GFX_diplomacy_status_is_subsidiary",
        "hidden": "yes",
        "term_data": {
          "resource_terms": {},
          "discrete_terms": {}
        },
        "overlord_weight": {
          "base": "150"
        },
        "subject_weight": {
          "base": "-250"
        },
        "potential": {
          "from": {}
        }
      },
      "<RECURSION>": 66
    },
    "preset_subsidiary_mean_03": {
      "preset_subsidiary_mean_03": {
        "parent": "preset_subsidiary",
        "icon": "GFX_diplomacy_status_is_subsidiary",
        "hidden": "yes",
        "term_data": {
          "resource_terms": {},
          "discrete_terms": {}
        },
        "overlord_weight": {
          "base": "175"
        },
        "subject_weight": {
          "base": "-500"
        },
        "potential": {
          "from": {}
        }
      },
      "<RECURSION>": 134
    },
    "preset_subsidiary_nice_01": {
      "preset_subsidiary_nice_01": {
        "parent": "preset_subsidiary",
        "icon": "GFX_diplomacy_status_is_subsidiary",
        "hidden": "yes",
        "term_data": {
          "resource_terms": {},
          "discrete_terms": {}
        },
        "overlord_weight": {
          "base": "75"
        },
        "subject_weight": {
          "base": "50"
        },
        "potential": {
          "from": {}
        }
      },
      "<RECURSION>": 206
    },
    "preset_subsidiary_nice_02": {
      "preset_subsidiary_nice_02": {
        "parent": "preset_subsidiary",
        "icon": "GFX_diplomacy_status_is_subsidiary",
        "hidden": "yes",
        "term_data": {
          "resource_terms": {},
          "discrete_terms": {}
        },
        "overlord_weight": {
          "base": "50"
        },
        "subject_weight": {
          "base": "100"
        },
        "potential": {
          "from": {}
        }
      },
      "<RECURSION>": 270
    }
  },
  "01_agreement_presets_ai_vassal.txt": {
    "preset_vassal_mean_01": {
      "preset_vassal_mean_01": {
        "parent": "preset_vassal",
        "icon": "GFX_diplomacy_status_is_vassal",
        "hidden": "yes",
        "term_data": {
          "discrete_terms": {}
        },
        "overlord_weight": {
          "base": "125"
        },
        "subject_weight": {
          "base": "-100"
        },
        "potential": {
          "from": {
            "NOR": {
              "is_megacorp": "yes",
              "is_country_type": "awakened_fallen_empire",
              "has_civic": "civic_inwards_perfection"
            }
          },
          "NOT": {
            "tech_unlocked_ratio": {
              "who": "from",
              "ratio >": "@protectorate_tech_threshold"
            }
          }
        }
      },
      "<RECURSION>": 4
    },
    "preset_vassal_mean_02": {
      "preset_vassal_mean_02": {
        "parent": "preset_vassal",
        "icon": "GFX_diplomacy_status_is_vassal",
        "hidden": "yes",
        "term_data": {
          "resource_terms": {},
          "discrete_terms": {}
        },
        "overlord_weight": {
          "base": "150"
        },
        "subject_weight": {
          "base": "-250"
        },
        "potential": {
          "from": {
            "NOR": {
              "is_megacorp": "yes",
              "is_country_type": "awakened_fallen_empire",
              "has_civic": "civic_inwards_perfection"
            }
          },
          "NOT": {
            "tech_unlocked_ratio": {
              "who": "from",
              "ratio >": "@protectorate_tech_threshold"
            }
          }
        }
      },
      "<RECURSION>": 73
    },
    "preset_vassal_mean_03": {
      "preset_vassal_mean_03": {
        "parent": "preset_vassal",
        "icon": "GFX_diplomacy_status_is_vassal",
        "hidden": "yes",
        "term_data": {
          "resource_terms": {},
          "discrete_terms": {}
        },
        "overlord_weight": {
          "base": "175"
        },
        "subject_weight": {
          "base": "-500"
        },
        "potential": {
          "from": {
            "NOR": {
              "is_megacorp": "yes",
              "is_country_type": "awakened_fallen_empire",
              "has_civic": "civic_inwards_perfection"
            }
          },
          "NOT": {
            "tech_unlocked_ratio": {
              "who": "from",
              "ratio >": "@protectorate_tech_threshold"
            }
          }
        }
      },
      "<RECURSION>": 152
    },
    "preset_vassal_nice_01": {
      "preset_vassal_nice_01": {
        "parent": "preset_vassal",
        "icon": "GFX_diplomacy_status_is_vassal",
        "hidden": "yes",
        "term_data": {
          "discrete_terms": {}
        },
        "overlord_weight": {
          "base": "75"
        },
        "subject_weight": {
          "base": "50"
        },
        "potential": {
          "from": {
            "NOR": {
              "is_megacorp": "yes",
              "is_country_type": "awakened_fallen_empire",
              "has_civic": "civic_inwards_perfection"
            }
          },
          "NOT": {
            "tech_unlocked_ratio": {
              "who": "from",
              "ratio >": "@protectorate_tech_threshold"
            }
          }
        }
      },
      "<RECURSION>": 235
    },
    "preset_vassal_nice_02": {
      "preset_vassal_nice_02": {
        "parent": "preset_vassal",
        "icon": "GFX_diplomacy_status_is_vassal",
        "hidden": "yes",
        "term_data": {
          "resource_terms": {},
          "discrete_terms": {}
        },
        "overlord_weight": {
          "base": "50"
        },
        "subject_weight": {
          "base": "100"
        },
        "potential": {
          "from": {
            "NOR": {
              "is_megacorp": "yes",
              "is_country_type": "awakened_fallen_empire",
              "has_civic": "civic_inwards_perfection"
            }
          },
          "NOT": {
            "tech_unlocked_ratio": {
              "who": "from",
              "ratio >": "@protectorate_tech_threshold"
            }
          }
        }
      },
      "<RECURSION>": 304
    }
  },
  "02_agreement_presets_ai_bulwark.txt": {
    "preset_bulwark_nice_01": {
      "preset_bulwark_nice_01": {
        "parent": "preset_bulwark",
        "specialist_type": "specialist_bulwark",
        "hidden": "yes",
        "term_data": {
          "discrete_terms": {}
        },
        "overlord_weight": {
          "base": "75",
          "modifier": {
            "factor": "0.5",
            "has_specialist_subject_type": {
              "NOT": {},
              "modifier": {
                "factor": "1.5",
                "FROM": {},
                "modifier": {
                  "add": "@specialist_unaligned_ethics_value",
                  "is_pacifist": "yes"
                }
              },
              "subject_weight": {
                "base": "50",
                "modifier": {
                  "add": "@specialist_unaligned_ethics_value",
                  "is_pacifist": "yes"
                }
              },
              "potential": {
                "has_overlord_dlc": "yes",
                "NOR": {
                  "has_civic": "civic_inwards_perfection",
                  "FROM": {},
                  "OR": {
                    "FROM": {
                      "is_specialist_subject_type": {
                        "tech_unlocked_ratio": {
                          "who": "from",
                          "ratio >": "@protectorate_tech_threshold"
                        }
                      }
                    }
                  }
                }
              }
            }
          }
        }
      },
      "<RECURSION>": 8
    },
    "preset_bulwark_nice_02": {
      "preset_bulwark_nice_02": {
        "parent": "preset_bulwark",
        "specialist_type": "specialist_bulwark",
        "hidden": "yes",
        "term_data": {
          "resource_terms": {},
          "discrete_terms": {}
        },
        "overlord_weight": {
          "base": "50",
          "modifier": {
            "factor": "0.5",
            "has_specialist_subject_type": {
              "NOT": {},
              "modifier": {
                "factor": "1.5",
                "FROM": {},
                "modifier": {
                  "add": "@specialist_unaligned_ethics_value",
                  "is_pacifist": "yes"
                }
              },
              "subject_weight": {
                "base": "100",
                "modifier": {
                  "add": "@specialist_unaligned_ethics_value",
                  "is_pacifist": "yes"
                }
              },
              "potential": {
                "has_overlord_dlc": "yes",
                "NOR": {
                  "has_civic": "civic_inwards_perfection",
                  "FROM": {},
                  "OR": {
                    "FROM": {
                      "is_specialist_subject_type": {
                        "tech_unlocked_ratio": {
                          "who": "from",
                          "ratio >": "@protectorate_tech_threshold"
                        }
                      }
                    }
                  }
                }
              }
            }
          }
        }
      },
      "<RECURSION>": "<RECURSION>"
    },
    "preset_bulwark_mean_01": {
      "preset_bulwark_mean_01": {
        "parent": "preset_bulwark",
        "specialist_type": "specialist_bulwark",
        "hidden": "yes",
        "term_data": {
          "discrete_terms": {}
        },
        "overlord_weight": {
          "base": "125",
          "modifier": {
            "factor": "0.5",
            "has_specialist_subject_type": {
              "NOT": {},
              "modifier": {
                "factor": "1.5",
                "FROM": {},
                "modifier": {
                  "add": "@specialist_unaligned_ethics_value",
                  "is_pacifist": "yes"
                }
              },
              "subject_weight": {
                "base": "-100",
                "modifier": {
                  "add": "@specialist_unaligned_ethics_value",
                  "is_pacifist": "yes"
                }
              },
              "potential": {
                "has_overlord_dlc": "yes",
                "NOR": {
                  "has_civic": "civic_inwards_perfection",
                  "FROM": {},
                  "OR": {
                    "FROM": {
                      "is_specialist_subject_type": {
                        "tech_unlocked_ratio": {
                          "who": "from",
                          "ratio >": "@protectorate_tech_threshold"
                        }
                      }
                    }
                  }
                }
              }
            }
          }
        }
      },
      "<RECURSION>": 218
    },
    "preset_bulwark_mean_02": {
      "preset_bulwark_mean_02": {
        "parent": "preset_bulwark",
        "specialist_type": "specialist_bulwark",
        "hidden": "yes",
        "term_data": {
          "discrete_terms": {}
        },
        "overlord_weight": {
          "base": "150",
          "modifier": {
            "factor": "0.5",
            "has_specialist_subject_type": {
              "NOT": {},
              "modifier": {
                "factor": "1.5",
                "FROM": {},
                "modifier": {
                  "add": "@specialist_unaligned_ethics_value",
                  "is_pacifist": "yes"
                }
              },
              "subject_weight": {
                "base": "-250",
                "modifier": {
                  "add": "@specialist_unaligned_ethics_value",
                  "is_pacifist": "yes"
                }
              },
              "potential": {
                "has_overlord_dlc": "yes",
                "NOR": {
                  "has_civic": "civic_inwards_perfection",
                  "FROM": {},
                  "OR": {
                    "FROM": {
                      "is_specialist_subject_type": {
                        "tech_unlocked_ratio": {
                          "who": "from",
                          "ratio >": "@protectorate_tech_threshold"
                        }
                      }
                    }
                  }
                }
              }
            }
          }
        }
      },
      "<RECURSION>": 318
    },
    "preset_bulwark_mean_03": {
      "preset_bulwark_mean_03": {
        "parent": "preset_bulwark",
        "specialist_type": "specialist_bulwark",
        "hidden": "yes",
        "term_data": {
          "discrete_terms": {}
        },
        "overlord_weight": {
          "base": "175",
          "modifier": {
            "factor": "0.5",
            "has_specialist_subject_type": {
              "NOT": {},
              "modifier": {
                "factor": "1.5",
                "FROM": {},
                "modifier": {
                  "add": "@specialist_unaligned_ethics_value",
                  "is_pacifist": "yes"
                }
              },
              "subject_weight": {
                "base": "-500",
                "modifier": {
                  "add": "@specialist_unaligned_ethics_value",
                  "is_pacifist": "yes"
                }
              },
              "potential": {
                "has_overlord_dlc": "yes",
                "NOR": {
                  "has_civic": "civic_inwards_perfection",
                  "FROM": {},
                  "OR": {
                    "FROM": {
                      "is_specialist_subject_type": {
                        "tech_unlocked_ratio": {
                          "who": "from",
                          "ratio >": "@protectorate_tech_threshold"
                        }
                      }
                    }
                  }
                }
              }
            }
          }
        }
      },
      "<RECURSION>": 418
    }
  },
  "03_agreement_presets_ai_scholarium.txt": {
    "preset_scholarium_nice_01": {
      "preset_scholarium_nice_01": {
        "parent": "preset_scholarium",
        "specialist_type": "specialist_scholarium",
        "hidden": "yes",
        "term_data": {
          "discrete_terms": {}
        },
        "overlord_weight": {
          "base": "75",
          "modifier": {
            "factor": "0.5",
            "has_specialist_subject_type": {
              "NOT": {},
              "modifier": {
                "factor": "1.5",
                "FROM": {},
                "modifier": {
                  "add": "@specialist_unaligned_ethics_value",
                  "is_spiritualist": "yes"
                }
              },
              "subject_weight": {
                "base": "50",
                "modifier": {
                  "add": "@specialist_unaligned_ethics_value",
                  "is_spiritualist": "yes"
                }
              },
              "potential": {
                "has_overlord_dlc": "yes",
                "NOR": {
                  "has_civic": "civic_inwards_perfection",
                  "FROM": {},
                  "OR": {
                    "FROM": {
                      "is_specialist_subject_type": {
                        "tech_unlocked_ratio": {
                          "who": "from",
                          "ratio >": "@protectorate_tech_threshold"
                        }
                      }
                    }
                  }
                }
              }
            }
          }
        }
      },
      "<RECURSION>": "<RECURSION>"
    },
    "preset_scholarium_nice_02": {
      "preset_scholarium_nice_02": {
        "parent": "preset_scholarium",
        "specialist_type": "specialist_scholarium",
        "hidden": "yes",
        "term_data": {
          "resource_terms": {},
          "discrete_terms": {}
        },
        "overlord_weight": {
          "base": "50",
          "modifier": {
            "factor": "0.5",
            "has_specialist_subject_type": {
              "NOT": {},
              "modifier": {
                "factor": "1.5",
                "FROM": {},
                "modifier": {
                  "add": "@specialist_unaligned_ethics_value",
                  "is_spiritualist": "yes"
                }
              },
              "subject_weight": {
                "base": "100",
                "modifier": {
                  "add": "@specialist_unaligned_ethics_value",
                  "is_spiritualist": "yes"
                }
              },
              "potential": {
                "has_overlord_dlc": "yes",
                "NOR": {
                  "has_civic": "civic_inwards_perfection",
                  "FROM": {},
                  "OR": {
                    "FROM": {
                      "is_specialist_subject_type": {
                        "tech_unlocked_ratio": {
                          "who": "from",
                          "ratio >": "@protectorate_tech_threshold"
                        }
                      }
                    }
                  }
                }
              }
            }
          }
        }
      },
      "<RECURSION>": 104
    },
    "preset_scholarium_mean_01": {
      "preset_scholarium_mean_01": {
        "parent": "preset_scholarium",
        "specialist_type": "specialist_scholarium",
        "hidden": "yes",
        "term_data": {
          "resource_terms": {},
          "discrete_terms": {}
        },
        "overlord_weight": {
          "base": "125",
          "modifier": {
            "factor": "0.5",
            "has_specialist_subject_type": {
              "NOT": {},
              "modifier": {
                "factor": "1.5",
                "FROM": {},
                "modifier": {
                  "add": "@specialist_unaligned_ethics_value",
                  "is_spiritualist": "yes"
                }
              },
              "subject_weight": {
                "base": "-100",
                "modifier": {
                  "add": "@specialist_unaligned_ethics_value",
                  "is_spiritualist": "yes"
                }
              },
              "potential": {
                "has_overlord_dlc": "yes",
                "NOR": {
                  "has_civic": "civic_inwards_perfection",
                  "FROM": {},
                  "OR": {
                    "FROM": {
                      "is_specialist_subject_type": {
                        "tech_unlocked_ratio": {
                          "who": "from",
                          "ratio >": "@protectorate_tech_threshold"
                        }
                      }
                    }
                  }
                }
              }
            }
          }
        }
      },
      "<RECURSION>": 210
    },
    "preset_scholarium_mean_02": {
      "preset_scholarium_mean_02": {
        "parent": "preset_scholarium",
        "specialist_type": "specialist_scholarium",
        "hidden": "yes",
        "term_data": {
          "resource_terms": {},
          "discrete_terms": {}
        },
        "overlord_weight": {
          "base": "150",
          "modifier": {
            "factor": "0.5",
            "has_specialist_subject_type": {
              "NOT": {},
              "modifier": {
                "factor": "1.5",
                "FROM": {},
                "modifier": {
                  "add": "@specialist_unaligned_ethics_value",
                  "is_spiritualist": "yes"
                }
              },
              "subject_weight": {
                "base": "-250",
                "modifier": {
                  "add": "@specialist_unaligned_ethics_value",
                  "is_spiritualist": "yes"
                }
              },
              "potential": {
                "has_overlord_dlc": "yes",
                "NOR": {
                  "has_civic": "civic_inwards_perfection",
                  "FROM": {},
                  "OR": {
                    "FROM": {
                      "is_specialist_subject_type": {
                        "tech_unlocked_ratio": {
                          "who": "from",
                          "ratio >": "@protectorate_tech_threshold"
                        }
                      }
                    }
                  }
                }
              }
            }
          }
        }
      },
      "<RECURSION>": 312
    },
    "preset_scholarium_mean_03": {
      "preset_scholarium_mean_03": {
        "parent": "preset_scholarium",
        "specialist_type": "specialist_scholarium",
        "hidden": "yes",
        "term_data": {
          "resource_terms": {},
          "discrete_terms": {}
        },
        "overlord_weight": {
          "base": "175",
          "modifier": {
            "factor": "0.5",
            "has_specialist_subject_type": {
              "NOT": {},
              "modifier": {
                "factor": "1.5",
                "FROM": {},
                "modifier": {
                  "add": "@specialist_unaligned_ethics_value",
                  "is_spiritualist": "yes"
                }
              },
              "subject_weight": {
                "base": "-500",
                "modifier": {
                  "add": "@specialist_unaligned_ethics_value",
                  "is_spiritualist": "yes"
                }
              },
              "potential": {
                "has_overlord_dlc": "yes",
                "NOR": {
                  "has_civic": "civic_inwards_perfection",
                  "FROM": {},
                  "OR": {
                    "FROM": {
                      "is_specialist_subject_type": {
                        "tech_unlocked_ratio": {
                          "who": "from",
                          "ratio >": "@protectorate_tech_threshold"
                        }
                      }
                    }
                  }
                }
              }
            }
          }
        }
      },
      "<RECURSION>": 413
    }
  },
  "04_agreement_presets_ai_prospectorium.txt": {
    "preset_prospectorium_nice_01": {
      "preset_prospectorium_nice_01": {
        "parent": "preset_prospectorium",
        "specialist_type": "specialist_prospectorium",
        "hidden": "yes",
        "term_data": {
          "discrete_terms": {}
        },
        "overlord_weight": {
          "base": "75",
          "modifier": {
            "factor": "0.5",
            "has_specialist_subject_type": {
              "NOT": {},
              "modifier": {
                "factor": "1.5",
                "FROM": {},
                "modifier": {
                  "add": "@specialist_unaligned_ethics_value",
                  "is_militarist": "yes"
                }
              },
              "subject_weight": {
                "base": "50",
                "modifier": {
                  "add": "@specialist_unaligned_ethics_value",
                  "is_militarist": "yes"
                }
              },
              "potential": {
                "has_overlord_dlc": "yes",
                "NOR": {
                  "has_civic": "civic_inwards_perfection",
                  "FROM": {},
                  "OR": {
                    "FROM": {
                      "is_specialist_subject_type": {
                        "tech_unlocked_ratio": {
                          "who": "from",
                          "ratio >": "@protectorate_tech_threshold"
                        }
                      }
                    }
                  }
                }
              }
            }
          }
        }
      },
      "<RECURSION>": 7
    },
    "preset_prospectorium_nice_02": {
      "preset_prospectorium_nice_02": {
        "parent": "preset_prospectorium",
        "specialist_type": "specialist_prospectorium",
        "hidden": "yes",
        "term_data": {
          "resource_terms": {},
          "discrete_terms": {}
        },
        "overlord_weight": {
          "base": "50",
          "modifier": {
            "factor": "0.5",
            "has_specialist_subject_type": {
              "NOT": {},
              "modifier": {
                "factor": "1.5",
                "FROM": {},
                "modifier": {
                  "add": "@specialist_unaligned_ethics_value",
                  "is_militarist": "yes"
                }
              },
              "subject_weight": {
                "base": "100",
                "modifier": {
                  "add": "@specialist_unaligned_ethics_value",
                  "is_militarist": "yes"
                }
              },
              "potential": {
                "has_overlord_dlc": "yes",
                "NOR": {
                  "has_civic": "civic_inwards_perfection",
                  "FROM": {},
                  "OR": {
                    "FROM": {
                      "is_specialist_subject_type": {
                        "tech_unlocked_ratio": {
                          "who": "from",
                          "ratio >": "@protectorate_tech_threshold"
                        }
                      }
                    }
                  }
                }
              }
            }
          }
        }
      },
      "<RECURSION>": 102
    },
    "preset_prospectorium_mean_01": {
      "preset_prospectorium_mean_01": {
        "parent": "preset_prospectorium",
        "specialist_type": "specialist_prospectorium",
        "hidden": "yes",
        "term_data": {
          "resource_terms": {},
          "discrete_terms": {}
        },
        "overlord_weight": {
          "base": "125",
          "modifier": {
            "factor": "0.5",
            "has_specialist_subject_type": {
              "NOT": {},
              "modifier": {
                "factor": "1.5",
                "FROM": {},
                "modifier": {
                  "add": "@specialist_unaligned_ethics_value",
                  "is_militarist": "yes"
                }
              },
              "subject_weight": {
                "base": "-100",
                "modifier": {
                  "add": "@specialist_unaligned_ethics_value",
                  "is_militarist": "yes"
                }
              },
              "potential": {
                "has_overlord_dlc": "yes",
                "NOR": {
                  "has_civic": "civic_inwards_perfection",
                  "FROM": {},
                  "OR": {
                    "FROM": {
                      "is_specialist_subject_type": {
                        "tech_unlocked_ratio": {
                          "who": "from",
                          "ratio >": "@protectorate_tech_threshold"
                        }
                      }
                    }
                  }
                }
              }
            }
          }
        }
      },
      "<RECURSION>": 207
    },
    "preset_prospectorium_mean_02": {
      "preset_prospectorium_mean_02": {
        "parent": "preset_prospectorium",
        "specialist_type": "specialist_prospectorium",
        "hidden": "yes",
        "term_data": {
          "resource_terms": {},
          "discrete_terms": {}
        },
        "overlord_weight": {
          "base": "150",
          "modifier": {
            "factor": "0.5",
            "has_specialist_subject_type": {
              "NOT": {},
              "modifier": {
                "factor": "1.5",
                "FROM": {},
                "modifier": {
                  "add": "@specialist_unaligned_ethics_value",
                  "is_militarist": "yes"
                }
              },
              "subject_weight": {
                "base": "-250",
                "modifier": {
                  "add": "@specialist_unaligned_ethics_value",
                  "is_militarist": "yes"
                }
              },
              "potential": {
                "has_overlord_dlc": "yes",
                "NOR": {
                  "has_civic": "civic_inwards_perfection",
                  "FROM": {},
                  "OR": {
                    "FROM": {
                      "is_specialist_subject_type": {
                        "tech_unlocked_ratio": {
                          "who": "from",
                          "ratio >": "@protectorate_tech_threshold"
                        }
                      }
                    }
                  }
                }
              }
            }
          }
        }
      },
      "<RECURSION>": 312
    },
    "preset_prospectorium_mean_03": {
      "preset_prospectorium_mean_03": {
        "parent": "preset_prospectorium",
        "specialist_type": "specialist_prospectorium",
        "hidden": "yes",
        "term_data": {
          "resource_terms": {},
          "discrete_terms": {}
        },
        "overlord_weight": {
          "base": "175",
          "modifier": {
            "factor": "0.5",
            "has_specialist_subject_type": {
              "NOT": {},
              "modifier": {
                "factor": "1.5",
                "FROM": {},
                "modifier": {
                  "add": "@specialist_unaligned_ethics_value",
                  "is_militarist": "yes"
                }
              },
              "subject_weight": {
                "base": "-500",
                "modifier": {
                  "add": "@specialist_unaligned_ethics_value",
                  "is_militarist": "yes"
                }
              },
              "potential": {
                "has_overlord_dlc": "yes",
                "NOR": {
                  "has_civic": "civic_inwards_perfection",
                  "FROM": {},
                  "OR": {
                    "FROM": {
                      "is_specialist_subject_type": {
                        "tech_unlocked_ratio": {
                          "who": "from",
                          "ratio >": "@protectorate_tech_threshold"
                        }
                      }
                    }
                  }
                }
              }
            }
          }
        }
      },
      "<RECURSION>": 421
    }
  },
  "05_agreement_presets_subjugation_wars.txt": {
    "preset_vassal_oppressive": {
      "preset_vassal_oppressive": {
        "parent": "preset_vassal",
        "icon": "GFX_diplomacy_status_is_vassal",
        "hidden": "yes",
        "term_data": {
          "has_cooldown_on_first_renegotiation": "no",
          "forced_initial_loyalty": "-100",
          "discrete_terms": {}
        },
        "overlord_weight": {
          "base": "0"
        },
        "subject_weight": {
          "base": "<RECURSION>"
        }
      },
      "<RECURSION>": 1
    },
    "preset_vassal_oppressive_ai": {
      "preset_vassal_oppressive_ai": {
        "parent": "preset_vassal",
        "icon": "GFX_diplomacy_status_is_vassal",
        "hidden": "yes",
        "term_data": {
          "has_cooldown_on_first_renegotiation": "no",
          "forced_initial_loyalty": "-100",
          "resource_terms": {},
          "discrete_terms": {}
        },
        "overlord_weight": {
          "base": "<RECURSION>"
        },
        "subject_weight": {
          "base": "<RECURSION>"
        }
      },
      "<RECURSION>": 57
    },
    "preset_vassal_balanced": {
      "preset_vassal_balanced": {
        "parent": "preset_vassal",
        "icon": "GFX_diplomacy_status_is_vassal",
        "hidden": "yes",
        "term_data": {
          "has_cooldown_on_first_renegotiation": "no",
          "forced_initial_loyalty": "-50",
          "discrete_terms": {}
        },
        "overlord_weight": {
          "base": "<RECURSION>"
        },
        "subject_weight": {
          "base": "<RECURSION>"
        }
      },
      "<RECURSION>": 119
    },
    "preset_vassal_benevolent": {
      "preset_vassal_benevolent": {
        "parent": "preset_vassal",
        "icon": "GFX_diplomacy_status_is_vassal",
        "hidden": "yes",
        "term_data": {
          "has_cooldown_on_first_renegotiation": "no",
          "forced_initial_loyalty": "<RECURSION>",
          "discrete_terms": {}
        },
        "overlord_weight": {
          "base": "<RECURSION>"
        },
        "subject_weight": {
          "base": "<RECURSION>"
        }
      },
      "<RECURSION>": 175
    },
    "preset_subsidiary_oppressive": {
      "preset_subsidiary_oppressive": {
        "parent": "preset_subsidiary",
        "icon": "GFX_diplomacy_status_is_subsidiary",
        "hidden": "yes",
        "term_data": {
          "has_cooldown_on_first_renegotiation": "no",
          "forced_initial_loyalty": "-100",
          "resource_terms": {},
          "discrete_terms": {}
        },
        "overlord_weight": {
          "base": "<RECURSION>"
        },
        "subject_weight": {
          "base": "<RECURSION>"
        }
      },
      "<RECURSION>": 230
    },
    "preset_subsidiary_oppressive_ai": {
      "preset_subsidiary_oppressive_ai": {
        "parent": "preset_subsidiary",
        "icon": "GFX_diplomacy_status_is_subsidiary",
        "hidden": "yes",
        "term_data": {
          "has_cooldown_on_first_renegotiation": "no",
          "forced_initial_loyalty": "-100",
          "resource_terms": {},
          "discrete_terms": {}
        },
        "overlord_weight": {
          "base": "<RECURSION>"
        },
        "subject_weight": {
          "base": "<RECURSION>"
        }
      },
      "<RECURSION>": 295
    },
    "preset_subsidiary_balanced": {
      "preset_subsidiary_balanced": {
        "parent": "preset_subsidiary",
        "icon": "GFX_diplomacy_status_is_subsidiary",
        "hidden": "yes",
        "term_data": {
          "has_cooldown_on_first_renegotiation": "no",
          "forced_initial_loyalty": "-50",
          "resource_terms": {},
          "discrete_terms": {}
        },
        "overlord_weight": {
          "base": "<RECURSION>"
        },
        "subject_weight": {
          "base": "<RECURSION>"
        }
      },
      "<RECURSION>": 357
    },
    "preset_subsidiary_benevolent": {
      "preset_subsidiary_benevolent": {
        "parent": "preset_subsidiary",
        "icon": "GFX_diplomacy_status_is_subsidiary",
        "hidden": "yes",
        "term_data": {
          "has_cooldown_on_first_renegotiation": "no",
          "forced_initial_loyalty": "<RECURSION>",
          "resource_terms": {},
          "discrete_terms": {}
        },
        "overlord_weight": {
          "base": "<RECURSION>"
        },
        "subject_weight": {
          "base": "<RECURSION>"
        }
      },
      "<RECURSION>": 419
    }
  },
  "06_agreement_presets_MSI.txt": {
    "preset_payback_subsidiary_oppressive": {
      "preset_payback_subsidiary_oppressive": {
        "parent": "preset_subsidiary",
        "icon": "GFX_diplomacy_status_is_subsidiary",
        "hidden": "yes",
        "term_data": {
          "has_cooldown_on_first_renegotiation": "no",
          "forced_initial_loyalty": "-100",
          "resource_terms": {},
          "discrete_terms": {}
        },
        "overlord_weight": {
          "base": "<RECURSION>"
        },
        "subject_weight": {
          "base": "<RECURSION>"
        }
      },
      "<RECURSION>": "<RECURSION>"
    },
    "preset_payback_subsidiary_balanced": {
      "preset_payback_subsidiary_balanced": {
        "parent": "preset_subsidiary",
        "icon": "GFX_diplomacy_status_is_subsidiary",
        "hidden": "yes",
        "term_data": {
          "has_cooldown_on_first_renegotiation": "no",
          "forced_initial_loyalty": "-50",
          "resource_terms": {},
          "discrete_terms": {}
        },
        "overlord_weight": {
          "base": "<RECURSION>"
        },
        "subject_weight": {
          "base": "<RECURSION>"
        }
      },
      "<RECURSION>": 67
    },
    "preset_payback_subsidiary_benevolent": {
      "preset_payback_subsidiary_benevolent": {
        "parent": "preset_subsidiary",
        "icon": "GFX_diplomacy_status_is_subsidiary",
        "hidden": "yes",
        "term_data": {
          "has_cooldown_on_first_renegotiation": "no",
          "forced_initial_loyalty": "<RECURSION>",
          "resource_terms": {},
          "discrete_terms": {}
        },
        "overlord_weight": {
          "base": "<RECURSION>"
        },
        "subject_weight": {
          "base": "<RECURSION>"
        }
      },
      "<RECURSION>": 129
    }
  },
  "07_agreement_presets_astral_planes.txt": {
    "preset_luminarium": {
      "preset_luminarium": {
        "icon": "GFX_diplomacy_status_is_luminarium",
        "term_data": {
          "discrete_terms": {}
        },
        "potential": {
          "exists": "event_target:formless_country",
          "is_same_value": "event_target:formless_country"
        },
        "should_ai_use_for_proposals": "no",
        "can_preset_be_changed": "no",
        "overlord_weight": {
          "base": "10000"
        },
        "subject_weight": {
          "base": "10000"
        }
      },
      "<RECURSION>": -1
    }
  }
}